{"total":3,"pageSize":10,"pageCount":1,"data":[{"title":"github1","slug":"github1","date":"2018-01-12T07:07:42.000Z","updated":"2018-01-12T07:09:49.034Z","comments":true,"path":"api/articles/github1.json","excerpt":"","keywords":null,"cover":"/2018/01/12/github1/timg.jpg","content":"<p><img src=\"/2018/01/12/github1/timg.jpg\" alt=\"123\"></p>\n","text":" [Figure] ","link":"","raw":null,"photos":[],"categories":[],"tags":[]},{"title":"利用github+hexo搭建个人博客","slug":"利用github-hexo搭建个人博客","date":"2018-01-12T03:37:17.000Z","updated":"2018-01-12T06:58:55.983Z","comments":true,"path":"api/articles/利用github-hexo搭建个人博客.json","excerpt":"","keywords":null,"cover":"/2018/01/12/利用github-hexo搭建个人博客/images/timg.jpg","content":"<h2 id=\"首先注册github账号\"><a href=\"#首先注册github账号\" class=\"headerlink\" title=\"首先注册github账号\"></a>首先注册github账号</h2><p>/home/mengtianhao/图片/2018-01-12 11-50-39 的屏幕截图.png<br><img src=\"/2018/01/12/利用github-hexo搭建个人博客/images/timg.jpg\" alt=\"\"></p>\n","text":"首先注册github账号/home/mengtianhao/图片/2018-01-12 11-50-39 的屏幕截图.png<br> [Figure] ","link":"","raw":null,"photos":[],"categories":[],"tags":[{"name":"blog","slug":"blog","count":1,"path":"api/tags/blog.json"},{"name":"markdown","slug":"markdown","count":1,"path":"api/tags/markdown.json"}]},{"title":"Hello World","slug":"hello-world","date":"2018-01-11T14:36:29.519Z","updated":"2018-01-11T14:36:29.519Z","comments":true,"path":"api/articles/hello-world.json","excerpt":"","keywords":null,"cover":null,"content":"<p>Welcome to <a href=\"https://hexo.io/\" target=\"_blank\" rel=\"noopener\">Hexo</a>! This is your very first post. Check <a href=\"https://hexo.io/docs/\" target=\"_blank\" rel=\"noopener\">documentation</a> for more info. If you get any problems when using Hexo, you can find the answer in <a href=\"https://hexo.io/docs/troubleshooting.html\" target=\"_blank\" rel=\"noopener\">troubleshooting</a> or you can ask me on <a href=\"https://github.com/hexojs/hexo/issues\" target=\"_blank\" rel=\"noopener\">GitHub</a>.</p>\n<h2 id=\"Quick-Start\"><a href=\"#Quick-Start\" class=\"headerlink\" title=\"Quick Start\"></a>Quick Start</h2><h3 id=\"Create-a-new-post\"><a href=\"#Create-a-new-post\" class=\"headerlink\" title=\"Create a new post\"></a>Create a new post</h3><figure class=\"highlight bash\"><table><tr><td class=\"gutter\"><pre><span class=\"line\">1</span><br></pre></td><td class=\"code\"><pre><span class=\"line\">$ hexo new <span class=\"string\">\"My New Post\"</span></span><br></pre></td></tr></table></figure>\n<p>More info: <a href=\"https://hexo.io/docs/writing.html\" target=\"_blank\" rel=\"noopener\">Writing</a></p>\n<h3 id=\"Run-server\"><a href=\"#Run-server\" class=\"headerlink\" title=\"Run server\"></a>Run server</h3><figure class=\"highlight bash\"><table><tr><td class=\"gutter\"><pre><span class=\"line\">1</span><br></pre></td><td class=\"code\"><pre><span class=\"line\">$ hexo server</span><br></pre></td></tr></table></figure>\n<p>More info: <a href=\"https://hexo.io/docs/server.html\" target=\"_blank\" rel=\"noopener\">Server</a></p>\n<h3 id=\"Generate-static-files\"><a href=\"#Generate-static-files\" class=\"headerlink\" title=\"Generate static files\"></a>Generate static files</h3><figure class=\"highlight bash\"><table><tr><td class=\"gutter\"><pre><span class=\"line\">1</span><br></pre></td><td class=\"code\"><pre><span class=\"line\">$ hexo generate</span><br></pre></td></tr></table></figure>\n<p>More info: <a href=\"https://hexo.io/docs/generating.html\" target=\"_blank\" rel=\"noopener\">Generating</a></p>\n<h3 id=\"Deploy-to-remote-sites\"><a href=\"#Deploy-to-remote-sites\" class=\"headerlink\" title=\"Deploy to remote sites\"></a>Deploy to remote sites</h3><figure class=\"highlight bash\"><table><tr><td class=\"gutter\"><pre><span class=\"line\">1</span><br></pre></td><td class=\"code\"><pre><span class=\"line\">$ hexo deploy</span><br></pre></td></tr></table></figure>\n<p>More info: <a href=\"https://hexo.io/docs/deployment.html\" target=\"_blank\" rel=\"noopener\">Deployment</a></p>\n","text":"Welcome to Hexo! This is your very first post. Check documentation for more info. If you get any problems when using Hexo, you can find the ","link":"","raw":null,"photos":[],"categories":[],"tags":[]}]}